MANIFEST.in
README
setup.py
airy/__init__.py
airy.egg-info/PKG-INFO
airy.egg-info/SOURCES.txt
airy.egg-info/dependency_links.txt
airy.egg-info/top_level.txt
airy/bin/airy-admin.py
airy/core/__init__.py
airy/core/admin.py
airy/core/conf.py
airy/core/context_processors.py
airy/core/db.py
airy/core/decorators.py
airy/core/exceptions.py
airy/core/manager.py
airy/core/markup.py
airy/core/monitor.py
airy/core/reportbug.py
airy/core/sanitizer.py
airy/core/validators.py
airy/core/ve.py
airy/core/web.py
airy/core/files/__init__.py
airy/core/files/base.py
airy/core/files/images.py
airy/core/files/locks.py
airy/core/files/move.py
airy/core/files/storage.py
airy/core/files/temp.py
airy/core/files/uploadedfile.py
airy/core/files/uploadhandler.py
airy/core/files/utils.py
airy/core/mail/__init__.py
airy/core/mail/message.py
airy/core/mail/utils.py
airy/core/mail/backends/__init__.py
airy/core/mail/backends/base.py
airy/core/mail/backends/console.py
airy/core/mail/backends/dummy.py
airy/core/mail/backends/filebased.py
airy/core/mail/backends/locmem.py
airy/core/mail/backends/smtp.py
airy/forms/__init__.py
airy/forms/fields.py
airy/forms/forms.py
airy/forms/formsets.py
airy/forms/util.py
airy/forms/widgets.py
airy/forms/extras/__init__.py
airy/forms/extras/widgets.py
airy/skeleton/app/__init__.py
airy/skeleton/app/handlers.py
airy/skeleton/app/models.py
airy/skeleton/app/urls.py
airy/skeleton/project/__init__.py
airy/skeleton/project/flashpolicy.xml
airy/skeleton/project/manage.py
airy/skeleton/project/requirements.pip
airy/skeleton/project/settings.py
airy/skeleton/project/static/images/profile-default-icon.png
airy/skeleton/project/static/images/profile-default.png
airy/skeleton/project/static/images/misc/button-gloss.png
airy/skeleton/project/static/images/misc/button-overlay.png
airy/skeleton/project/static/images/misc/custom-form-sprites.png
airy/skeleton/project/static/images/misc/input-bg.png
airy/skeleton/project/static/images/misc/modal-gloss.png
airy/skeleton/project/static/images/misc/table-sorter.png
airy/skeleton/project/static/images/orbit/bullets.jpg
