Metadata-Version: 1.1
Name: airy
Version: 0.1.3
Summary: Web Application Framework
Home-page: http://airy.letolab.com
Author: LetoLab Ltd
Author-email: team@letolab.com
License: BSD
Keywords: web development websockets
Platform: UNKNOWN
Classifier: Programming Language :: Python
Classifier: Topic :: Internet :: WWW/HTTP
Classifier: Topic :: Utilities
Classifier: License :: OSI Approved :: BSD License
Classifier: Development Status :: 3 - Alpha
Requires: simplejson
Requires: ipython
